MANIFEST.in
README.md
requirements.txt
setup.py
periods/__init__.py
periods/day.py
periods/halfyear.py
periods/month.py
periods/period.py
periods/quarter.py
periods/week.py
periods/year.py
python_periods.egg-info/PKG-INFO
python_periods.egg-info/SOURCES.txt
python_periods.egg-info/dependency_links.txt
python_periods.egg-info/requires.txt
python_periods.egg-info/top_level.txt