Metadata-Version: 1.1
Name: python-periods
Version: 0.1.5
Summary: Some convenient classes and methods for working with time periods
Home-page: https://github.com/iloob/python-periods
Author: Olof Sjöbergh
Author-email: olofsj@gmail.com
License: MIT
Platform: UNKNOWN
Classifier: Development Status :: 5 - Production/Stable
Classifier: Intended Audience :: Developers
Classifier: License :: OSI Approved :: MIT License
